minimonolith_schema/__init__.py
minimonolith_schema/pdf_layout.py
minimonolith_schema/plot_columns.py
minimonolith_schema/print_metrics.py
minimonolith_schema/validators.py
minimonolith_schema-0.3.4.dist-info/LICENSE.txt
minimonolith_schema-0.3.4.dist-info/METADATA
minimonolith_schema-0.3.4.dist-info/WHEEL
minimonolith_schema-0.3.4.dist-info/top_level.txt
minimonolith_schema-0.3.4.dist-info/RECORD
